LICENSE
MANIFEST.in
README.md
pyproject.toml
setup.cfg
setup.py
functional_sampling_tool.egg-info/PKG-INFO
functional_sampling_tool.egg-info/SOURCES.txt
functional_sampling_tool.egg-info/dependency_links.txt
functional_sampling_tool.egg-info/entry_points.txt
functional_sampling_tool.egg-info/requires.txt
functional_sampling_tool.egg-info/top_level.txt
lib/_ctransformations.cpp
lib/_ctransformations.pyx
src/__init__.py
src/choosing.py
src/clustering.py
src/cmd_line.py
src/default_config.py
src/epoch_starting.py
src/exceptions.py
src/inout.py
src/transformations.py
src/utils.py
src/analysis/__init__.py
src/analysis/ancestry.py
src/analysis/extract.py
src/analysis/parsers.py
src/templates/config_example.py.txt
src/templates/sbatch_template.sh