Metadata-Version: 2.4
Name: functional_sampling_tool
Version: 0.0.10
Summary: A tool for enhancing sampling in MD-simulations
Home-page: https://github.com/molecularmachinist/functional_sampling_tool
Author: Santeri Paajanen, Shreyas Kaptan
Author-email: santeri.e.paajanen@helsinki.fi
License: MIT
Project-URL: Bug Tracker, https://github.com/molecularmachinist/functional_sampling_tool/issues
Classifier: Programming Language :: Python :: 3
Classifier: Programming Language :: Cython
Classifier: Operating System :: OS Independent
Classifier: License :: OSI Approved :: MIT License
Requires-Python: >=3.7
License-File: LICENSE
Requires-Dist: scikit-learn>=1.0
Requires-Dist: matplotlib>=3.2
Requires-Dist: numpy>=1.21
Requires-Dist: scipy>=1.1.0
Requires-Dist: MDAnalysis>=2.4
Requires-Dist: networkx>=2.5
Requires-Dist: pygraphviz>=1.5
Requires-Dist: importlib_resources>=4.0; python_version < "3.10"
Dynamic: license-file
